litelookup/__init__.py
litelookup/chat.py
litelookup/config/__init__.py
litelookup/config/config.py
litelookup/config/directory.py
litelookup/config/model.py
litelookup/format.py
litelookup/llm.py
litelookup/log/__init__.py
litelookup/log/config.json
litelookup/log/logging_config.py
litelookup/main.py
litelookup/responses.py
litelookup-0.21.6.dist-info/LICENSE
litelookup-0.21.6.dist-info/METADATA
litelookup-0.21.6.dist-info/WHEEL
litelookup-0.21.6.dist-info/entry_points.txt
litelookup-0.21.6.dist-info/RECORD
