Metadata-Version: 2.3
Name: litelookup
Version: 0.21.6
Summary: A command line tool for quick concept lookups
Requires-Python: >=3.12
Classifier: Programming Language :: Python :: 3
Classifier: Programming Language :: Python :: 3.12
Classifier: Programming Language :: Python :: 3.13
Requires-Dist: groq (>=0.24.0)
Requires-Dist: httpx[http2] (>=0.28.1)
Requires-Dist: langchain (==0.3.0)
Requires-Dist: langchain-core (>=0.3.56)
Requires-Dist: langchain-groq (>=0.2.5)
Requires-Dist: prompt-toolkit (>=3.0.51)
Requires-Dist: pytest (>=8.3.5)
Requires-Dist: python-dotenv (>=1.1.0)
Requires-Dist: redis (>=6.0.0)
Requires-Dist: rich (>=14.0.0)
